Workbook

Sheet Inputs
A1: Budgeting Inputs
A3: Assumptions
A5: Target Month (yyyy-mm) | B5: 2025-10
A6: IRS Mileage Rate ($/mile) | B6: 0.67
A7: Avg Gas Price ($/gal) | B7: 3.45
A8: Vehicle MPG | B8: 28
A9: Maintenance Reserve ($/mile) | B9: 0.08
A11: Monthly Income Targets | D11: Monthly Fixed Bills (Personal)
A12: DoorDash | B12: 1200 | D12: Rent/Mortgage (Personal) | E12: 900
A13: UberEats | B13: 900 | D13: Utilities (Elec/Gas/Water) | E13: 220
A14: Spark | B14: 1100 | D14: Internet/Phone | E14: 120
A15: Roadie | B15: 400 | D15: Auto Insurance | E15: 110
A16: Other Personal Income | B16: 300 | D16: Subscriptions (Spotify/Netflix/etc.) | E16: 30
A17: Rental Net (after mortgage) | B17: 800 | D17: Groceries (Base) | E17: 350
D18: Fuel (Base) | E18: 220
D19: Debt Payments | E19: 150

Sheet Monthly Budget
A1: Monthly Budget — Plan
A2: Month | B2: =Inputs!B5
A4: Planned Income
A5: Category | B5: Planned
A6: DoorDash | B6: =Inputs!B12
A7: UberEats | B7: =Inputs!B13
A8: Spark | B8: =Inputs!B14
A9: Roadie | B9: =Inputs!B15
A10: Other Personal Income | B10: =Inputs!B16
A11: Rental Net (after mortgage) | B11: =Inputs!B17
A12: Total Income | B12: =SUM(B6:B11)
A14: Planned Expenses
A15: Category | B15: Planned
A16: Rent/Mortgage (Personal) | B16: =Inputs!E12
A17: Utilities | B17: =Inputs!E13
A18: Internet/Phone | B18: =Inputs!E14
A19: Auto Insurance | B19: =Inputs!E15
A20: Subscriptions | B20: =Inputs!E16
A21: Groceries | B21: =Inputs!E17
A22: Fuel | B22: =Inputs!E18
A23: Debt Payments | B23: =Inputs!E19
A24: Car Maintenance Reserve | B24: =(Inputs!B9*Inputs!B8)*100
A25: Tolls/Parking | B25: 40
A26: Supplies (Bags/Straps/Tape) | B26: 25
A27: Apps/Tools (Pro) | B27: 25
A28: Marketing/Promo | B28: 30
A29: Repairs Reserve (Rental) | B29: 150
A30: Landscaping/Trash (Rental) | B30: 60
A31: Vacancy Reserve (Rental) | B31: 100
A32: Emergency Fund | B32: 150
A33: Vehicle Replacement Fund | B33: 150
A34: Investments | B34: 75
A35: Total Expenses | B35: =SUM(B15:B34)
A36: Planned Net | B36: =B12-B35

Sheet Actuals
A1: Transactions (Actuals)
A3: Date | B3: Description | C3: Type | D3: Platform | E3: Category | F3: Amount | G3: Miles | H3: Notes | I3: Month
I4: =TEXT(A4,"yyyy-mm")
I5: =TEXT(A5,"yyyy-mm")
I6: =TEXT(A6,"yyyy-mm")
I7: =TEXT(A7,"yyyy-mm")
I8: =TEXT(A8,"yyyy-mm")
I9: =TEXT(A9,"yyyy-mm")
I10: =TEXT(A10,"yyyy-mm")
I11: =TEXT(A11,"yyyy-mm")
I12: =TEXT(A12,"yyyy-mm")
I13: =TEXT(A13,"yyyy-mm")
I14: =TEXT(A14,"yyyy-mm")
I15: =TEXT(A15,"yyyy-mm")
... I199: =TEXT(A199,"yyyy-mm")

Sheet Summary
A1: Budget Summary
A3: Month (yyyy-mm) | B3: =Inputs!B5
A5: Planned vs Actual — Income
A6: Category | B6: Planned | C6: Actual | D6: Variance
A7: DoorDash | B7: =INDEX(Monthly Budget!B6:B11, MATCH("DoorDash", Monthly Budget!A6:A11, 0)) | C7: =SUMIFS(Actuals!F:F, Actuals!I:I, $B$3, Actuals!C:C, "Income", Actuals!D:D, "DoorDash") | D7: =C7-B7
A8: UberEats | B8: =INDEX(Monthly Budget!B6:B11, MATCH("UberEats", Monthly Budget!A6:A11, 0)) | C8: =SUMIFS(Actuals!F:F, Actuals!I:I, $B$3, Actuals!C:C, "Income", Actuals!D:D, "UberEats") | D8: =C8-B8
A9: Spark | B9: =INDEX(Monthly Budget!B6:B11, MATCH("Spark", Monthly Budget!A6:A11, 0)) | C9: =SUMIFS(Actuals!F:F, Actuals!I:I, $B$3, Actuals!C:C, "Income", Actuals!D:D, "Spark") | D9: =C9-B9
A10: Roadie | B10: =INDEX(Monthly Budget!B6:B11, MATCH("Roadie", Monthly Budget!A6:A11, 0)) | C10: =SUMIFS(Actuals!F:F, Actuals!I:I, $B$3, Actuals!C:C, "Income", Actuals!D:D, "Roadie") | D10: =C10-B10
A11: Other Personal Income | B11: =INDEX(Monthly Budget!B6:B11, MATCH("Other Personal Income", Monthly Budget!A6:A11, 0)) | C11: =SUMIFS(Actuals!F:F, Actuals!I:I, $B$3, Actuals!C:C, "Income", Actuals!D:D, "Other") | D11: =C11-B11
A12: Rental Net (after mortgage) | B12: =INDEX(Monthly Budget!B6:B11, MATCH("Rental Net (after mortgage)", Monthly Budget!A6:A11, 0)) | C12: =SUMIFS(Actuals!F:F, Actuals!I:I, $B$3, Actuals!C:C, "Income", Actuals!D:D, "Rental Net (after mortgage)") | D12: =C12-B12
A13: Total Income | B13: =SUM(B7:B12) | C13: =SUM(C7:C12) | D13: =C13-B13
A15: Planned vs Actual — Expenses
A16: Category | B16: Planned | C16: Actual | D16: Variance
A17: Rent/Mortgage (Personal) | B17: =INDEX(Monthly Budget!B15:B33, MATCH("Rent/Mortgage (Personal)", Monthly Budget!A15:A33, 0)) | C17: =SUMIFS(Actuals!F:F, Actuals!I:I, $B$3, Actuals!C:C, "Expense", Actuals!E:E, "Rent/Mortgage (Personal)") | D17: =C17-B17
A18: Utilities | B18: =INDEX(Monthly Budget!B15:B33, MATCH("Utilities", Monthly Budget!A15:A33, 0)) | C18: =SUMIFS(Actuals!F:F, Actuals!I:I, $B$3, Actuals!C:C, "Expense", Actuals!E:E, "Utilities") | D18: =C18-B18
A19: Internet/Phone | B19: =INDEX(Monthly Budget!B15:B33, MATCH("Internet/Phone", Monthly Budget!A15:A33, 0)) | C19: =SUMIFS(Actuals!F:F, Actuals!I:I, $B$3, Actuals!C:C, "Expense", Actuals!E:E, "Internet/Phone") | D19: =C19-B19
A20: Auto Insurance | B20: =INDEX(Monthly Budget!B15:B33, MATCH("Auto Insurance", Monthly Budget!A15:A33, 0)) | C20: =SUMIFS(Actuals!F:F, Actuals!I:I, $B$3, Actuals!C:C, "Expense", Actuals!E:E, "Auto Insurance") | D20: =C20-B20
A21: Subscriptions | B21: =INDEX(Monthly Budget!B15:B33, MATCH("Subscriptions", Monthly Budget!A15:A33, 0)) | C21: =SUMIFS(Actuals!F:F, Actuals!I:I, $B$3, Actuals!C:C, "Expense", Actuals!E:E, "Subscriptions") | D21: =C21-B21
A22: Groceries | B22: =INDEX(Monthly Budget!B15:B33, MATCH("Groceries", Monthly Budget!A15:A33, 0)) | C22: =SUMIFS(Actuals!F:F, Actuals!I:I, $B$3, Actuals!C:C, "Expense", Actuals!E:E, "Groceries") | D22: =C22-B22
A23: Fuel | B23: =INDEX(Monthly Budget!B15:B33, MATCH("Fuel", Monthly Budget!A15:A33, 0)) | C23: =SUMIFS(Actuals!F:F, Actuals!I:I, $B$3, Actuals!C:C, "Expense", Actuals!E:E, "Fuel") | D23: =C23-B23
A24: Debt Payments | B24: =INDEX(Monthly Budget!B15:B33, MATCH("Debt Payments", Monthly Budget!A15:A33, 0)) | C24: =SUMIFS(Actuals!F:F, Actuals!I:I, $B$3, Actuals!C:C, "Expense", Actuals!E:E, "Debt Payments") | D24: =C24-B24
A25: Car Maintenance Reserve | B25: =INDEX(Monthly Budget!B15:B33, MATCH("Car Maintenance Reserve", Monthly Budget!A15:A33, 0)) | C25: =SUMIFS(Actuals!F:F, Actuals!I:I, $B$3, Actuals!C:C, "Expense", Actuals!E:E, "Car Maintenance Reserve") | D25: =C25-B25
A26: Tolls/Parking | B26: =INDEX(Monthly Budget!B15:B33, MATCH("Tolls/Parking", Monthly Budget!A15:A33, 0)) | C26: =SUMIFS(Actuals!F:F, Actuals!I:I, $B$3, Actuals!C:C, "Expense", Actuals!E:E, "Tolls/Parking") | D26: =C26-B26
A27: Supplies (Bags/Straps/Tape) | B27: =INDEX(Monthly Budget!B15:B33, MATCH("Supplies (Bags/Straps/Tape)", Monthly Budget!A15:A33, 0)) | C27: =SUMIFS(Actuals!F:F, Actuals!I:I, $B$3, Actuals!C:C, "Expense", Actuals!E:E, "Supplies (Bags/Straps/Tape)") | D27: =C27-B27
A28: Apps/Tools (Pro) | B28: =INDEX(Monthly Budget!B15:B33, MATCH("Apps/Tools (Pro)", Monthly Budget!A15:A33, 0)) | C28: =SUMIFS(Actuals!F:F, Actuals!I:I, $B$3, Actuals!C:C, "Expense", Actuals!E:E, "Apps/Tools (Pro)") | D28: =C28-B28
A29: Marketing/Promo | B29: =INDEX(Monthly Budget!B15:B33, MATCH("Marketing/Promo", Monthly Budget!A15:A33, 0)) | C29: =SUMIFS(Actuals!F:F, Actuals!I:I, $B$3, Actuals!C:C, "Expense", Actuals!E:E, "Marketing/Promo") | D29: =C29-B29
A30: Repairs Reserve (Rental) | B30: =INDEX(Monthly Budget!B15:B33, MATCH("Repairs Reserve (Rental)", Monthly Budget!A15:A33, 0)) | C30: =SUMIFS(Actuals!F:F, Actuals!I:I, $B$3, Actuals!C:C, "Expense", Actuals!E:E, "Repairs Reserve (Rental)") | D30: =C30-B30
A31: Landscaping/Trash (Rental) | B31: =INDEX(Monthly Budget!B15:B33, MATCH("Landscaping/Trash (Rental)", Monthly Budget!A15:A33, 0)) | C31: =SUMIFS(Actuals!F:F, Actuals!I:I, $B$3, Actuals!C:C, "Expense", Actuals!E:E, "Landscaping/Trash (Rental)") | D31: =C31-B31
A32: Vacancy Reserve (Rental) | B32: =INDEX(Monthly Budget!B15:B33, MATCH("Vacancy Reserve (Rental)", Monthly Budget!A15:A33, 0)) | C32: =SUMIFS(Actuals!F:F, Actuals!I:I, $B$3, Actuals!C:C, "Expense", Actuals!E:E, "Vacancy Reserve (Rental)") | D32: =C32-B32
A33: Emergency Fund | B33: =INDEX(Monthly Budget!B15:B33, MATCH("Emergency Fund", Monthly Budget!A15:A33, 0)) | C33: =SUMIFS(Actuals!F:F, Actuals!I:I, $B$3, Actuals!C:C, "Expense", Actuals!E:E, "Emergency Fund") | D33: =C33-B33
A34: Vehicle Replacement Fund | B34: =INDEX(Monthly Budget!B15:B33, MATCH("Vehicle Replacement Fund", Monthly Budget!A15:A33, 0)) | C34: =SUMIFS(Actuals!F:F, Actuals!I:I, $B$3, Actuals!C:C, "Expense", Actuals!E:E, "Vehicle Replacement Fund") | D34: =C34-B34
A35: Investments | B35: =INDEX(Monthly Budget!B15:B33, MATCH("Investments", Monthly Budget!A15:A33, 0)) | C35: =SUMIFS(Actuals!F:F, Actuals!I:I, $B$3, Actuals!C:C, "Expense", Actuals!E:E, "Investments") | D35: =C35-B35
A36: Total Expenses | B36: =SUM(B17:B35) | C36: =SUM(C17:C35) | D36: =C36-B36
A38: Net (Income - Expenses) | B38: =B13-B35 | C38: =C13-C35 | D38: =C38-B38
